dentopy/__init__.py
dentopy/main.py
dentopy-0.1.3.dist-info/LICENSE
dentopy-0.1.3.dist-info/METADATA
dentopy-0.1.3.dist-info/WHEEL
dentopy-0.1.3.dist-info/entry_points.txt
dentopy-0.1.3.dist-info/RECORD
