Metadata-Version: 2.1
Name: dentopy
Version: 0.1.3
Summary: 
Author: harsh-leen
Author-email: harsh@leen.dev
Requires-Python: >=3.10,<4.0
Classifier: Programming Language :: Python :: 3
Classifier: Programming Language :: Python :: 3.10
Classifier: Programming Language :: Python :: 3.11
Classifier: Programming Language :: Python :: 3.12
Requires-Dist: click (>=8.1.7,<9.0.0)
Requires-Dist: pydantic (>=2.6.3,<3.0.0)
